odoo/addons/stock_quant_history/README.rst
odoo/addons/stock_quant_history/__init__.py
odoo/addons/stock_quant_history/__manifest__.py
odoo/addons/stock_quant_history/i18n/fr.po
odoo/addons/stock_quant_history/i18n/it.po
odoo/addons/stock_quant_history/i18n/nl.po
odoo/addons/stock_quant_history/i18n/stock_quant_history.pot
odoo/addons/stock_quant_history/models/__init__.py
odoo/addons/stock_quant_history/models/stock_quant_history.py
odoo/addons/stock_quant_history/models/stock_quant_history_snapshot.py
odoo/addons/stock_quant_history/readme/CONSTRIBUTORS.rst
odoo/addons/stock_quant_history/readme/DESCRIPTION.md
odoo/addons/stock_quant_history/readme/ROADMAP.md
odoo/addons/stock_quant_history/readme/USAGE.md
odoo/addons/stock_quant_history/security/ir.model.access.csv
odoo/addons/stock_quant_history/static/description/icon.png
odoo/addons/stock_quant_history/static/description/index.html
odoo/addons/stock_quant_history/tests/__init__.py
odoo/addons/stock_quant_history/tests/test_stock_quant_history.py
odoo/addons/stock_quant_history/views/stock-quant-history-snapshot.xml
odoo/addons/stock_quant_history/views/stock-quant-history.xml
odoo_addon_stock_quant_history-17.0.1.0.0.5.dist-info/METADATA
odoo_addon_stock_quant_history-17.0.1.0.0.5.dist-info/WHEEL
odoo_addon_stock_quant_history-17.0.1.0.0.5.dist-info/top_level.txt
odoo_addon_stock_quant_history-17.0.1.0.0.5.dist-info/RECORD
